octodns_autodns/__init__.py
octodns_autodns-0.0.2.dist-info/LICENSE
octodns_autodns-0.0.2.dist-info/METADATA
octodns_autodns-0.0.2.dist-info/WHEEL
octodns_autodns-0.0.2.dist-info/top_level.txt
octodns_autodns-0.0.2.dist-info/RECORD
