Metadata-Version: 2.2
Name: octodns-autodns
Version: 0.0.2
Summary:  AutoDNS provider for octoDNS
Home-page: https://github.com/octodns/octodns-autodns
Author: Christoph Sieber, Martin Neubert, Martin Schurz, Christopher Grau
Author-email: christoph.sieber@telekom.de, martin.neubert@telekom.de, martin.schurz@telekom.de, c.grau@telekom.de
License: MIT
Requires-Python: >=3.9
License-File: LICENSE
Requires-Dist: octodns>=1.0.0
Requires-Dist: requests>=2.32.3
Provides-Extra: dev
Requires-Dist: pytest; extra == "dev"
Requires-Dist: pytest-cov; extra == "dev"
Requires-Dist: pytest-network; extra == "dev"
Requires-Dist: requests_mock; extra == "dev"
Requires-Dist: black<25.0.0,>=24.3.0; extra == "dev"
Requires-Dist: build>=0.7.0; extra == "dev"
Requires-Dist: isort>=5.11.5; extra == "dev"
Requires-Dist: pyflakes>=2.2.0; extra == "dev"
Requires-Dist: readme_renderer[md]>=26.0; extra == "dev"
Requires-Dist: twine>=3.4.2; extra == "dev"
Provides-Extra: test
Requires-Dist: pytest; extra == "test"
Requires-Dist: pytest-cov; extra == "test"
Requires-Dist: pytest-network; extra == "test"
Requires-Dist: requests_mock; extra == "test"
Dynamic: author
Dynamic: author-email
Dynamic: description
Dynamic: description-content-type
Dynamic: home-page
Dynamic: license
Dynamic: provides-extra
Dynamic: requires-dist
Dynamic: requires-python
Dynamic: summary
